odoo/addons/product_multi_company/README.rst
odoo/addons/product_multi_company/__init__.py
odoo/addons/product_multi_company/__manifest__.py
odoo/addons/product_multi_company/hooks.py
odoo/addons/product_multi_company/i18n/es.po
odoo/addons/product_multi_company/i18n/fr.po
odoo/addons/product_multi_company/i18n/hr.po
odoo/addons/product_multi_company/i18n/it.po
odoo/addons/product_multi_company/i18n/nl_NL.po
odoo/addons/product_multi_company/i18n/product_multi_company.pot
odoo/addons/product_multi_company/i18n/pt.po
odoo/addons/product_multi_company/i18n/tr.po
odoo/addons/product_multi_company/migrations/18.0.1.0.0/pre-migrate.py
odoo/addons/product_multi_company/models/__init__.py
odoo/addons/product_multi_company/models/product_template.py
odoo/addons/product_multi_company/readme/CONTRIBUTORS.md
odoo/addons/product_multi_company/readme/DESCRIPTION.md
odoo/addons/product_multi_company/readme/INSTALL.md
odoo/addons/product_multi_company/readme/USAGE.md
odoo/addons/product_multi_company/static/description/icon.png
odoo/addons/product_multi_company/static/description/index.html
odoo/addons/product_multi_company/tests/__init__.py
odoo/addons/product_multi_company/tests/common.py
odoo/addons/product_multi_company/tests/test_product_multi_company.py
odoo/addons/product_multi_company/views/product_template_view.xml
odoo_addon_product_multi_company-18.0.1.0.0.3.dist-info/METADATA
odoo_addon_product_multi_company-18.0.1.0.0.3.dist-info/WHEEL
odoo_addon_product_multi_company-18.0.1.0.0.3.dist-info/top_level.txt
odoo_addon_product_multi_company-18.0.1.0.0.3.dist-info/RECORD
