Metadata-Version: 2.1
Name: odoo-addon-product_multi_company
Version: 18.0.1.0.0.3
Requires-Python: >=3.10
Requires-Dist: odoo-addon-base_multi_company==18.0.*
Requires-Dist: odoo==18.0.*
Summary: Select individually the product template visibility on each company
Home-page: https://github.com/OCA/multi-company
License: AGPL-3
Author: Tecnativa,Odoo Community Association (OCA)
Author-email: support@odoo-community.org
Classifier: Programming Language :: Python
Classifier: Framework :: Odoo
Classifier: Framework :: Odoo :: 18.0
Classifier: License :: OSI Approved :: GNU Affero General Public License v3
